pretty_jupyter_metadata_form/__init__.py
pretty_jupyter_metadata_form/_version.py
pretty_jupyter_metadata_form-1.0.5.data/data/share/jupyter/labextensions/@jans-code/pretty_jupyter_metadata_form/package.json
pretty_jupyter_metadata_form-1.0.5.data/data/share/jupyter/labextensions/@jans-code/pretty_jupyter_metadata_form/schemas/@jans-code/pretty_jupyter_metadata_form/package.json.orig
pretty_jupyter_metadata_form-1.0.5.data/data/share/jupyter/labextensions/@jans-code/pretty_jupyter_metadata_form/schemas/@jans-code/pretty_jupyter_metadata_form/pjmdf.json
pretty_jupyter_metadata_form-1.0.5.data/data/share/jupyter/labextensions/@jans-code/pretty_jupyter_metadata_form/static/509.765dc87c6cf27ccf815b.js
pretty_jupyter_metadata_form-1.0.5.data/data/share/jupyter/labextensions/@jans-code/pretty_jupyter_metadata_form/static/728.56c222902258a3a381a1.js
pretty_jupyter_metadata_form-1.0.5.data/data/share/jupyter/labextensions/@jans-code/pretty_jupyter_metadata_form/static/remoteEntry.fe4cd402775bb2eccc3d.js
pretty_jupyter_metadata_form-1.0.5.data/data/share/jupyter/labextensions/@jans-code/pretty_jupyter_metadata_form/static/style.js
pretty_jupyter_metadata_form-1.0.5.data/data/share/jupyter/labextensions/@jans-code/pretty_jupyter_metadata_form/static/third-party-licenses.json
pretty_jupyter_metadata_form-1.0.5.data/data/share/jupyter/labextensions/@jans-code/pretty_jupyter_metadata_form/install.json
pretty_jupyter_metadata_form-1.0.5.dist-info/METADATA
pretty_jupyter_metadata_form-1.0.5.dist-info/WHEEL
pretty_jupyter_metadata_form-1.0.5.dist-info/licenses/LICENSE
pretty_jupyter_metadata_form-1.0.5.dist-info/RECORD
